l10n_traceback-0.0.1.dist-info/METADATA
l10n_traceback-0.0.1.dist-info/WHEEL
l10n_traceback-0.0.1.dist-info/licenses/LICENSE
l10n_traceback/__init__.py
l10n_traceback/color.py
l10n_traceback/error.py
l10n_traceback-0.0.1.dist-info/RECORD
