Metadata-Version: 2.1
Name: l10n_traceback
Version: 0.0.1
Summary: 将 python 的报错翻译成中文 translate python traceback to chinese
Author-Email: F-park <1527093924@qq.com>
License: MIT
Project-URL: Homepage, https://github.com/F-park/l10n_traceback
Project-URL: Issues, https://github.com/F-park/l10n_traceback/issues
Requires-Python: >=3.8
